pyframex/__init__.py
pyframex/__main__.py
pyframex/columns.py
pyframex/frame.py
pyframex/ml.py
pyframex/query.py
pyframex-0.1.0.dist-info/licenses/LICENSE
pyframex-0.1.0.dist-info/METADATA
pyframex-0.1.0.dist-info/WHEEL
pyframex-0.1.0.dist-info/entry_points.txt
pyframex-0.1.0.dist-info/top_level.txt
pyframex-0.1.0.dist-info/RECORD
