Metadata-Version: 2.4
Name: pyframex
Version: 0.1.0
Summary: Next-generation native DataFrame for Python - Simple like Excel, Powerful like SQL, Smart like AI
Home-page: https://github.com/idrissbado/PyFrameX
Author: Idriss Bado
Author-email: Idriss Bado <idrissbadoolivier@gmail.com>
License: MIT
Project-URL: Homepage, https://github.com/idrissbado/PyFrameX
Project-URL: Documentation, https://github.com/idrissbado/PyFrameX#readme
Project-URL: Repository, https://github.com/idrissbado/PyFrameX
Project-URL: Bug Tracker, https://github.com/idrissbado/PyFrameX/issues
Keywords: dataframe,data,analysis,sql,machine-learning,excel,pandas-alternative
Classifier: Development Status :: 4 - Beta
Classifier: Intended Audience :: Developers
Classifier: Intended Audience :: Science/Research
Classifier: License :: OSI Approved :: MIT License
Classifier: Programming Language :: Python :: 3
Classifier: Programming Language :: Python :: 3.8
Classifier: Programming Language :: Python :: 3.9
Classifier: Programming Language :: Python :: 3.10
Classifier: Programming Language :: Python :: 3.11
Classifier: Programming Language :: Python :: 3.12
Classifier: Topic :: Scientific/Engineering
Classifier: Topic :: Software Development :: Libraries :: Python Modules
Requires-Python: >=3.8
License-File: LICENSE
Provides-Extra: ml
Requires-Dist: scikit-learn>=1.0.0; extra == "ml"
Provides-Extra: all
Requires-Dist: scikit-learn>=1.0.0; extra == "all"
Dynamic: author
Dynamic: home-page
Dynamic: license-file
Dynamic: requires-python
